{
	"id": "806eb756-e9b3-42fc-b682-0158d158b6fe",
	"name": "GetQuantitiesFromStock_ep_CURL",
	"description": "Get Stock for DEMO UPDATE",
	"context": "/getQuantitiesFromStock_ep_curl",
	"version": "2.2.0",
	"provider": "lendl",
	"apiDefinition": "{\"paths\":{\"/*\":{\"post\":{\"parameters\":[{\"schema\":{\"type\":\"string\"},\"description\":\"SOAP request.\",\"name\":\"SOAP Request\",\"required\":true,\"in\":\"body\"},{\"description\":\"SOAPAction header for soap 1.1\",\"name\":\"SOAPAction\",\"type\":\"string\",\"required\":false,\"in\":\"header\"}],\"responses\":{\"200\":{\"description\":\"OK\"}},\"x-auth-type\":\"Application & Application User\",\"x-throttling-tier\":\"Unlimited\"}}},\"swagger\":\"2.0\",\"consumes\":[\"text/xml\",\"application/soap+xml\"],\"produces\":[\"text/xml\",\"application/soap+xml\"],\"info\":{\"title\":\"DNA\",\"version\":\"1.0\",\"description\":\"DNA WSDL\"}}",
	"wsdlUri": "/registry/resource/_system/governance/apimgt/applicationdata/wsdls/admin--GetQuantitiesFromStock_ep_CURL1.1.0.wsdl",
	"status": "CREATED",
	"responseCaching": "Disabled",
	"cacheTimeout": 300,
	"destinationStatsEnabled": null,
	"isDefaultVersion": false,
	"type": "HTTP",
	"transport": ["http",
	"https"],
	"tags": ["Codes",
	"Stocks","API"],
	"tiers": ["Gold"],
	"maxTps": {
		"sandbox": 5000,
		"production": 1000
	},
	"thumbnailUri": null,
	"visibility": "PUBLIC",
	"visibleRoles": [],
	"visibleTenants": [],
	"endpointConfig": "{\"production_endpoints\":{\"url\":\"http://dil-preprod.dna.fi/soa-infra/services/default/GetQuantitiesFromStockService!1.0/GetQuantitiesFromStock_ep\",\"config\":null},\"sandbox_endpoints\":{\"url\":\"http://dil-preprod.dna.fi/soa-infra/services/default/GetQuantitiesFromStockService!1.0/GetQuantitiesFromStock_ep\",\"config\":null},\"endpoint_type\":\"http\"}",
	"endpointSecurity": {
		"username": "dna_dsg",
		"type": "basic",
		"password": "SAaT7IGrAR"
	},
	"gatewayEnvironments": "Production and Sandbox",
	"sequences": [],
	"subscriptionAvailability": null,
	"subscriptionAvailableTenants": [],
	"businessInformation": {
		"businessOwnerEmail": "marketing@dna.com",
		"technicalOwnerEmail": "architecture@dna.com",
		"technicalOwner": "Lendl Gomes",
		"businessOwner": "Leo Gomes"
	},
	"corsConfiguration": {
		"accessControlAllowOrigins": ["*"],
		"accessControlAllowHeaders": ["authorization",
		"Access-Control-Allow-Origin",
		"Content-Type",
		"SOAPAction"],
		"accessControlAllowMethods": ["GET",
		"PUT",
		"POST",
		"DELETE",
		"PATCH",
		"OPTIONS"],
		"accessControlAllowCredentials": false,
		"corsConfigurationEnabled": false
	}
}
